docker_compose_all.py
docker_compose_all-0.2.2.dist-info/LICENSE
docker_compose_all-0.2.2.dist-info/METADATA
docker_compose_all-0.2.2.dist-info/WHEEL
docker_compose_all-0.2.2.dist-info/entry_points.txt
docker_compose_all-0.2.2.dist-info/top_level.txt
docker_compose_all-0.2.2.dist-info/RECORD
